pyramid_georest/__init__.py
pyramid_georest/routes.py
pyramid_georest/lib/__init__.py
pyramid_georest/lib/database.py
pyramid_georest/lib/description.py
pyramid_georest/lib/renderer.py
pyramid_georest/lib/rest.py
pyramid_georest-3.1.1.dist-info/LICENSE.txt
pyramid_georest-3.1.1.dist-info/METADATA
pyramid_georest-3.1.1.dist-info/WHEEL
pyramid_georest-3.1.1.dist-info/entry_points.txt
pyramid_georest-3.1.1.dist-info/top_level.txt
pyramid_georest-3.1.1.dist-info/RECORD
