Metadata-Version: 2.1
Name: pyramid-georest
Version: 3.1.1
Summary: pyramid_georest, extension for pyramid web frame work to provide rest interface for sql-alchemy mappers
Home-page: https://github.com/vvmruder/pyramid_georest
Author: Clemens Rudert
Author-email: clemens.rudert@bl.ch
License: GNU General Public License
Keywords: web pyramid pylons rest sqlalchemy orm model geoalchemy
Platform: UNKNOWN
Classifier: Development Status :: 5 - Production/Stable
Classifier: Intended Audience :: Developers
Classifier: Programming Language :: Python :: 2.7
Classifier: Programming Language :: Python :: 3.6
Classifier: Framework :: Pyramid
Classifier: Topic :: Internet :: WWW/HTTP
Classifier: Topic :: Internet :: WWW/HTTP :: WSGI :: Application
Requires-Dist: pyramid
Requires-Dist: SQLAlchemy
Requires-Dist: shapely
Requires-Dist: dicttoxml
Requires-Dist: GeoAlchemy2
Requires-Dist: transaction
Requires-Dist: waitress
Requires-Dist: pyramid-debugtoolbar
Requires-Dist: zope.sqlalchemy
Requires-Dist: PyYAML
Requires-Dist: psycopg2
Requires-Dist: simplejson
Provides-Extra: testing
Requires-Dist: WebTest (>=1.3.1) ; extra == 'testing'
Requires-Dist: pytest ; extra == 'testing'
Requires-Dist: pytest-cov ; extra == 'testing'
